ansible_tests/__init__.py
ansible_tests/__main__.py
ansible_tests/testinfra_launcher.py
ansible_tests/yaml_loader.py
ansible_tests-0.0.4.dist-info/LICENSE
ansible_tests-0.0.4.dist-info/METADATA
ansible_tests-0.0.4.dist-info/WHEEL
ansible_tests-0.0.4.dist-info/entry_points.txt
ansible_tests-0.0.4.dist-info/top_level.txt
ansible_tests-0.0.4.dist-info/RECORD
