Metadata-Version: 2.1
Name: ansible-tests
Version: 0.0.4
Summary: UNKNOWN
Home-page: https://github.com/TanguyPatte/ansible-tests.git
Author: Tanguy Patte
License: UNKNOWN
Platform: UNKNOWN
Requires-Dist: click
Requires-Dist: pyyaml
Requires-Dist: testinfra
Requires-Dist: ansible
